[
    {
        "company_names": "KÖZMŰÚT J.K.K. Építő és Szolgáltató Kft.; SWIETELSKY Építő Kft.",
        "contract_value": 156859736.0,
        "contracting_authority": "Budapest Főváros XVI. Kerületi Önkormányzat",
        "date": "02/11/2020",
        "link_notice": "http://www.kozbeszerzes.hu/ertesito/2020/0/targy/portal_454/megtekint/portal_19874_2020/",
        "main_cpv": "45233120-6",
        "number_companies_win": 2,
        "procurement_title": "Budapest XVI. kerületi útépítések LII.",
        "registered_name": "KÖZMŰÚT J.K.K. Építő és Szolgáltató Kft."
    },
    {
        "company_names": "KÖZMŰÚT J.K.K. Építő és Szolgáltató Kft.; SWIETELSKY Építő Kft.",
        "contract_value": 137722125.0,
        "contracting_authority": "Budapest Főváros XVI. Kerületi Önkormányzat",
        "date": "02/11/2020",
        "link_notice": "http://www.kozbeszerzes.hu/ertesito/2020/0/targy/portal_454/megtekint/portal_19874_2020/",
        "main_cpv": "45233120-6",
        "number_companies_win": 2,
        "procurement_title": "Budapest XVI. kerületi útépítések LII.",
        "registered_name": "KÖZMŰÚT J.K.K. Építő és Szolgáltató Kft."
    },
    {
        "company_names": "KÖZMŰÚT J.K.K. Építő és Szolgáltató Kft.; SWIETELSKY Építő Kft.",
        "contract_value": 116936794.0,
        "contracting_authority": "Budapest Főváros XVI. Kerületi Önkormányzat",
        "date": "08/09/2021",
        "link_notice": "https://www.kozbeszerzes.hu/ertesito/2021/0/targy/portal_454/megtekint/portal_17235_2021/",
        "main_cpv": "45233120-6",
        "number_companies_win": 2,
        "procurement_title": "Budapest XVI. kerületi útépítések LXI.",
        "registered_name": "KÖZMŰÚT J.K.K. Építő és Szolgáltató Kft."
    },
    {
        "company_names": "KÖZMŰÚT J.K.K. Építő és Szolgáltató Kft.; SWIETELSKY Magyarország Kft.",
        "contract_value": 103253240.0,
        "contracting_authority": "Budapest Főváros XVI. Kerületi Önkormányzat",
        "date": "14/04/2020",
        "link_notice": "http://www.kozbeszerzes.hu/ertesito/2020/0/targy/portal_434/megtekint/portal_6427_2020/",
        "main_cpv": "45233120-6",
        "number_companies_win": 2,
        "procurement_title": "Budapest XVI. kerületi útépítések XLIX.",
        "registered_name": "KÖZMŰÚT J.K.K. Építő és Szolgáltató Kft."
    },
    {
        "company_names": "KÖZMŰÚT J.K.K. Építő és Szolgáltató Kft.; SWIETELSKY Építő Kft.",
        "contract_value": 60197534.0,
        "contracting_authority": "Budapest Főváros XVI. Kerületi Önkormányzat",
        "date": "02/11/2020",
        "link_notice": "http://www.kozbeszerzes.hu/ertesito/2020/0/targy/portal_454/megtekint/portal_19877_2020/",
        "main_cpv": "45233120-6",
        "number_companies_win": 2,
        "procurement_title": "Budapest XVI. kerületi útépítések LVI.",
        "registered_name": "KÖZMŰÚT J.K.K. Építő és Szolgáltató Kft."
    },
    {
        "company_names": "",
        "contract_value": 57823842.0,
        "contracting_authority": "Budapest Főváros XVI. Kerületi Önkormányzat",
        "date": "21/10/2021",
        "link_notice": "https://www.kozbeszerzes.hu/ertesito/2021/0/targy/portal_454/megtekint/portal_20481_2021/",
        "main_cpv": "45233120-6",
        "number_companies_win": 0,
        "procurement_title": "Budapest XVI. kerületi útépítések LXIII.",
        "registered_name": "KÖZMŰÚT J.K.K. Építő és Szolgáltató Kft."
    },
    {
        "company_names": "",
        "contract_value": 50227136.0,
        "contracting_authority": "Budapest Főváros XVI. Kerületi Önkormányzat",
        "date": "28/10/2021",
        "link_notice": "https://www.kozbeszerzes.hu/ertesito/2021/0/targy/portal_454/megtekint/portal_21005_2021/",
        "main_cpv": "45233120-6",
        "number_companies_win": 0,
        "procurement_title": "Budapest XVI. kerületi útépítések LXII.",
        "registered_name": "KÖZMŰÚT J.K.K. Építő és Szolgáltató Kft."
    },
    {
        "company_names": "KÖZMŰÚT J.K.K. Építő és Szolgáltató Kft.; SWIETELSKY Építő Kft.",
        "contract_value": 47301686.0,
        "contracting_authority": "Budapest Főváros XVI. Kerületi Önkormányzat",
        "date": "17/03/2020",
        "link_notice": "http://www.kozbeszerzes.hu/ertesito/2020/0/targy/portal_434/megtekint/portal_4467_2020/",
        "main_cpv": "45233120-6",
        "number_companies_win": 2,
        "procurement_title": "Budapest XVI. kerületi útépítések XLVIII.",
        "registered_name": "KÖZMŰÚT J.K.K. Építő és Szolgáltató Kft."
    },
    {
        "company_names": "",
        "contract_value": 37792920.0,
        "contracting_authority": "Budapest Főváros XVI. Kerületi Önkormányzat",
        "date": "08/09/2021",
        "link_notice": "https://www.kozbeszerzes.hu/ertesito/2021/0/targy/portal_454/megtekint/portal_17235_2021/",
        "main_cpv": "45233120-6",
        "number_companies_win": 0,
        "procurement_title": "Budapest XVI. kerületi útépítések LXI.",
        "registered_name": "KÖZMŰÚT J.K.K. Építő és Szolgáltató Kft."
    },
    {
        "company_names": "KÖZMŰÚT J.K.K. Építő és Szolgáltató Kft.; SWIETELSKY Építő Kft.",
        "contract_value": 31092332.0,
        "contracting_authority": "Budapest Főváros XVI. Kerületi Önkormányzat",
        "date": "16/04/2021",
        "link_notice": "https://www.kozbeszerzes.hu/ertesito/2021/0/targy/portal_454/megtekint/portal_6547_2021/",
        "main_cpv": "45233120-6",
        "number_companies_win": 2,
        "procurement_title": "Budapest XVI. kerületi útépítések LVII.",
        "registered_name": "KÖZMŰÚT J.K.K. Építő és Szolgáltató Kft."
    },
    {
        "company_names": "KÖZMŰÚT J.K.K. Építő és Szolgáltató Kft.; SWIETELSKY Építő Kft.",
        "contract_value": 29387575.0,
        "contracting_authority": "Budapest Főváros XVI. Kerületi Önkormányzat",
        "date": "04/12/2020",
        "link_notice": "http://www.kozbeszerzes.hu/ertesito/2020/0/targy/portal_454/megtekint/portal_22456_2020/",
        "main_cpv": "45233223-8",
        "number_companies_win": 2,
        "procurement_title": "Budapest XVI. kerületi burkolat-felújítások - 2020",
        "registered_name": "KÖZMŰÚT J.K.K. Építő és Szolgáltató Kft."
    },
    {
        "company_names": "KÖZMŰÚT J.K.K. Építő és Szolgáltató Kft.; SWIETELSKY Építő Kft.",
        "contract_value": 28375725.0,
        "contracting_authority": "Budapest Főváros XVI. Kerületi Önkormányzat",
        "date": "16/04/2021",
        "link_notice": "https://www.kozbeszerzes.hu/ertesito/2021/0/targy/portal_454/megtekint/portal_6547_2021/",
        "main_cpv": "45233120-6",
        "number_companies_win": 2,
        "procurement_title": "Budapest XVI. kerületi útépítések LVII.",
        "registered_name": "KÖZMŰÚT J.K.K. Építő és Szolgáltató Kft."
    },
    {
        "company_names": "KÖZMŰÚT J.K.K. Építő és Szolgáltató Kft.; SWIETELSKY Építő Kft.",
        "contract_value": 14589272.0,
        "contracting_authority": "Budapest Főváros XVI. Kerületi Önkormányzat",
        "date": "17/03/2020",
        "link_notice": "http://www.kozbeszerzes.hu/ertesito/2020/0/targy/portal_434/megtekint/portal_4467_2020/",
        "main_cpv": "45233120-6",
        "number_companies_win": 2,
        "procurement_title": "Budapest XVI. kerületi útépítések XLVIII.",
        "registered_name": "KÖZMŰÚT J.K.K. Építő és Szolgáltató Kft."
    }
]