[
    {
        "company_names": "",
        "contract_value": 180447560.0,
        "contracting_authority": "Balatonfűzfő Város Önkormányzata Szivárvány Óvoda és Bölcsőde",
        "date": "15/01/2019",
        "link_notice": "http://www.kozbeszerzes.hu/ertesito/2019/0/targy/portal_434/megtekint/portal_0684_2019/",
        "main_cpv": "55510000-8",
        "number_companies_win": 0,
        "procurement_title": "Közétkeztetés 4 évre",
        "registered_name": "Bakony GASZT Kereskedelmi, Vendéglátó és Szolgáltató Zrt."
    },
    {
        "company_names": "",
        "contract_value": 139972260.0,
        "contracting_authority": "Balatonfűzfő Város Önkormányzata",
        "date": "18/01/2019",
        "link_notice": "https://kozbeszerzes.hu/adatbazis/megtekint/hirdetmeny/portal_0685_2019/",
        "main_cpv": "55510000-8",
        "number_companies_win": 0,
        "procurement_title": "Közétkeztetés 4 évre",
        "registered_name": "Bakony GASZT Kereskedelmi, Vendéglátó és Szolgáltató Zrt."
    },
    {
        "company_names": "",
        "contract_value": 505051555.0,
        "contracting_authority": "Veszprémi Intézményi Szolgáltató Szervezet",
        "date": "30/06/2020",
        "link_notice": "http://www.kozbeszerzes.hu/ertesito/2020/0/targy/portal_421/megtekint/portal_11230_2020/",
        "main_cpv": "55520000-1",
        "number_companies_win": 0,
        "procurement_title": "Közétkeztetési feladatok ellátása",
        "registered_name": "Bakony GASZT Kereskedelmi, Vendéglátó és Szolgáltató Zrt."
    },
    {
        "company_names": "",
        "contract_value": 355505931.0,
        "contracting_authority": "Balatonalmádi Városgondnokság",
        "date": "09/12/2020",
        "link_notice": "http://www.kozbeszerzes.hu/ertesito/2020/0/targy/portal_421/megtekint/portal_22543_2020/",
        "main_cpv": "55524000-9",
        "number_companies_win": 0,
        "procurement_title": "Vásárolt élelmezési szolgáltatások beszerzés",
        "registered_name": "Bakony GASZT Kereskedelmi, Vendéglátó és Szolgáltató Zrt."
    }
]