[
    {
        "company_names": "",
        "contract_value": 54236160.0,
        "contracting_authority": "Szántód Község Önkormányzata",
        "date": "18/05/2018",
        "link_notice": "http://www.kozbeszerzes.hu/ertesito/2018/0/targy/portal_434/megtekint/portal_8236_2018/",
        "main_cpv": "45000000-7",
        "number_companies_win": 0,
        "procurement_title": "Út- és járda-felújítási munkák beszerzése Szántód Község Önkormányzata részére",
        "registered_name": "BALATON-ÚT Építő, Szolgáltató és Kereskedelmi Kft."
    },
    {
        "company_names": "",
        "contract_value": 76414250.0,
        "contracting_authority": "Balatonboglár Városi Önkormányzat",
        "date": "06/06/2018",
        "link_notice": "http://www.kozbeszerzes.hu/ertesito/2018/0/targy/portal_434/megtekint/portal_9342_2018/",
        "main_cpv": "45000000-7",
        "number_companies_win": 0,
        "procurement_title": "Római út II. útépítés megrendelése",
        "registered_name": "BALATON-ÚT Építő, Szolgáltató és Kereskedelmi Kft."
    },
    {
        "company_names": "",
        "contract_value": 35029111.0,
        "contracting_authority": "Balatonboglár Városi Önkormányzat",
        "date": "01/10/2018",
        "link_notice": "http://www.kozbeszerzes.hu/ertesito/2018/0/targy/portal_434/megtekint/portal_17796_2018/",
        "main_cpv": "45000000-7",
        "number_companies_win": 0,
        "procurement_title": "Útfelújítás - a balatonboglári Gyep utca-Klapka Gy. utca és Zrínyi M. utca közötti szakasz felújítása",
        "registered_name": "BALATON-ÚT Építő, Szolgáltató és Kereskedelmi Kft."
    },
    {
        "company_names": "",
        "contract_value": 247480826.0,
        "contracting_authority": "Balatonboglár Városi Önkormányzat",
        "date": "22/01/2019",
        "link_notice": "http://www.kozbeszerzes.hu/ertesito/2019/0/targy/portal_434/megtekint/portal_1188_2019/",
        "main_cpv": "45000000-7",
        "number_companies_win": 0,
        "procurement_title": "Platán Strand fejlesztése-TOP",
        "registered_name": "BALATON-ÚT Építő, Szolgáltató és Kereskedelmi Kft."
    },
    {
        "company_names": "",
        "contract_value": 6893500.0,
        "contracting_authority": "Felsőmocsolád Község Önkormányzata",
        "date": "27/03/2019",
        "link_notice": "http://www.kozbeszerzes.hu/ertesito/2019/0/targy/portal_434/megtekint/portal_5178_2019/",
        "main_cpv": "45233228-3",
        "number_companies_win": 0,
        "procurement_title": "Vis maior eseményhez kötődő helyreállítási munkák",
        "registered_name": "BALATON-ÚT Építő, Szolgáltató és Kereskedelmi Kft."
    },
    {
        "company_names": "",
        "contract_value": 8954200.0,
        "contracting_authority": "Felsőmocsolád Község Önkormányzata",
        "date": "27/03/2019",
        "link_notice": "http://www.kozbeszerzes.hu/ertesito/2019/0/targy/portal_434/megtekint/portal_5178_2019/",
        "main_cpv": "45233228-3",
        "number_companies_win": 0,
        "procurement_title": "Vis maior eseményhez kötődő helyreállítási munkák",
        "registered_name": "BALATON-ÚT Építő, Szolgáltató és Kereskedelmi Kft."
    },
    {
        "company_names": "",
        "contract_value": 13167600.0,
        "contracting_authority": "Felsőmocsolád Község Önkormányzata",
        "date": "27/03/2019",
        "link_notice": "http://www.kozbeszerzes.hu/ertesito/2019/0/targy/portal_434/megtekint/portal_5178_2019/",
        "main_cpv": "45233228-3",
        "number_companies_win": 0,
        "procurement_title": "Vis maior eseményhez kötődő helyreállítási munkák",
        "registered_name": "BALATON-ÚT Építő, Szolgáltató és Kereskedelmi Kft."
    },
    {
        "company_names": "",
        "contract_value": 75503993.0,
        "contracting_authority": "Lengyeltóti Város Önkormányzata",
        "date": "16/04/2019",
        "link_notice": "http://www.kozbeszerzes.hu/ertesito/2019/0/targy/portal_434/megtekint/portal_6749_2019/",
        "main_cpv": "45000000-7",
        "number_companies_win": 0,
        "procurement_title": "Zöld város kialakítása Lengyeltótiban",
        "registered_name": "BALATON-ÚT Építő, Szolgáltató és Kereskedelmi Kft."
    },
    {
        "company_names": "",
        "contract_value": 9869900.0,
        "contracting_authority": "Felsőmocsolád Község Önkormányzata",
        "date": "10/09/2019",
        "link_notice": "http://www.kozbeszerzes.hu/ertesito/2019/0/targy/portal_434/megtekint/portal_17011_2019/",
        "main_cpv": "45000000-7",
        "number_companies_win": 0,
        "procurement_title": "Petőfi S. utca és Malom utca útfelújítása",
        "registered_name": "BALATON-ÚT Építő, Szolgáltató és Kereskedelmi Kft."
    },
    {
        "company_names": "",
        "contract_value": 8124210.0,
        "contracting_authority": "Szántód Község Önkormányzata",
        "date": "18/09/2019",
        "link_notice": "https://www.kozbeszerzes.hu/ertesito/2019/0/targy/portal_434/megtekint/portal_17796_2019/",
        "main_cpv": "45000000-7",
        "number_companies_win": 0,
        "procurement_title": "Út- és járdafelújítás, parkolóépítés",
        "registered_name": "BALATON-ÚT Építő, Szolgáltató és Kereskedelmi Kft."
    },
    {
        "company_names": "",
        "contract_value": 43297675.0,
        "contracting_authority": "Balatonboglár Városi Önkormányzat",
        "date": "18/09/2019",
        "link_notice": "https://www.kozbeszerzes.hu/ertesito/2019/0/targy/portal_434/megtekint/portal_17522_2019/",
        "main_cpv": "45000000-7",
        "number_companies_win": 0,
        "procurement_title": "Gaál Gaszton utca felújítása",
        "registered_name": "BALATON-ÚT Építő, Szolgáltató és Kereskedelmi Kft."
    },
    {
        "company_names": "",
        "contract_value": 48896339.0,
        "contracting_authority": "Szántód Község Önkormányzata",
        "date": "18/09/2019",
        "link_notice": "https://www.kozbeszerzes.hu/ertesito/2019/0/targy/portal_434/megtekint/portal_17796_2019/",
        "main_cpv": "45000000-7",
        "number_companies_win": 0,
        "procurement_title": "Út- és járdafelújítás, parkolóépítés",
        "registered_name": "BALATON-ÚT Építő, Szolgáltató és Kereskedelmi Kft."
    },
    {
        "company_names": "",
        "contract_value": 5949215.0,
        "contracting_authority": "Ecseny Község Önkormányzata",
        "date": "16/10/2019",
        "link_notice": "http://www.kozbeszerzes.hu/ertesito/2019/0/targy/portal_434/megtekint/portal_20070_2019/",
        "main_cpv": "45233228-3",
        "number_companies_win": 0,
        "procurement_title": "Polány, Somogygeszti, Ecseny külterületi útfelújítás",
        "registered_name": "BALATON-ÚT Építő, Szolgáltató és Kereskedelmi Kft."
    },
    {
        "company_names": "",
        "contract_value": 71178135.0,
        "contracting_authority": "Ecseny Község Önkormányzata",
        "date": "16/10/2019",
        "link_notice": "http://www.kozbeszerzes.hu/ertesito/2019/0/targy/portal_434/megtekint/portal_20070_2019/",
        "main_cpv": "45233228-3",
        "number_companies_win": 0,
        "procurement_title": "Polány, Somogygeszti, Ecseny külterületi útfelújítás",
        "registered_name": "BALATON-ÚT Építő, Szolgáltató és Kereskedelmi Kft."
    },
    {
        "company_names": "",
        "contract_value": 228628439.0,
        "contracting_authority": "Balatonboglár Városi Önkormányzat",
        "date": "06/11/2019",
        "link_notice": "http://www.kozbeszerzes.hu/ertesito/2019/0/targy/portal_434/megtekint/portal_21083_2019/",
        "main_cpv": "45000000-7",
        "number_companies_win": 0,
        "procurement_title": "Platán Park fejlesztése",
        "registered_name": "BALATON-ÚT Építő, Szolgáltató és Kereskedelmi Kft."
    }
]