[
    {
        "company_names": "",
        "contract_value": 66153108.0,
        "contracting_authority": "Martonfa Község Önkormányzata",
        "date": "29/01/2018",
        "link_notice": "http://www.kozbeszerzes.hu/ertesito/2017/0/targy/portal_434/megtekint/portal_19550_2017/",
        "main_cpv": "45232400-6",
        "number_companies_win": 0,
        "procurement_title": "Építési beruházás a Martonfa Község Önkormányzata Martonfa szennyvízkezelése című VP-6-7.2.1.2-16 azonosító számú projektre vonatkozóan",
        "registered_name": "Z. E. H. Energetikai és Építőipari Kft."
    },
    {
        "company_names": "",
        "contract_value": 119344498.0,
        "contracting_authority": "Mindszentgodisa Községi Önkormányzat",
        "date": "29/01/2018",
        "link_notice": "http://www.kozbeszerzes.hu/ertesito/2017/0/targy/portal_434/megtekint/portal_19549_2017/",
        "main_cpv": "45232400-6",
        "number_companies_win": 0,
        "procurement_title": "Mindszentgodisa Község szennyvízkezelési beruházása",
        "registered_name": "Z. E. H. Energetikai és Építőipari Kft."
    },
    {
        "company_names": "",
        "contract_value": 136589712.0,
        "contracting_authority": "Szenna Község Önkormányzata",
        "date": "29/01/2018",
        "link_notice": "http://www.kozbeszerzes.hu/ertesito/2017/0/targy/portal_434/megtekint/portal_19548_2017/",
        "main_cpv": "45232420-2",
        "number_companies_win": 0,
        "procurement_title": "Egyedi szennyvíztisztítók kiépítése Szennán",
        "registered_name": "Z. E. H. Energetikai és Építőipari Kft."
    },
    {
        "company_names": "",
        "contract_value": 119344498.0,
        "contracting_authority": "Mindszentgodisa Községi Önkormányzat",
        "date": "02/02/2018",
        "link_notice": "http://www.kozbeszerzes.hu/ertesito/2018/0/targy/portal_434/megtekint/portal_1784_2018/",
        "main_cpv": "45000000-7",
        "number_companies_win": 0,
        "procurement_title": "Mindszentgodisa Község szennyvízkezelési beruházása",
        "registered_name": "Z. E. H. Energetikai és Építőipari Kft."
    },
    {
        "company_names": "",
        "contract_value": 136589712.0,
        "contracting_authority": "Szenna Község Önkormányzata",
        "date": "02/02/2018",
        "link_notice": "http://www.kozbeszerzes.hu/ertesito/2018/0/targy/portal_434/megtekint/portal_1788_2018/",
        "main_cpv": "45000000-7",
        "number_companies_win": 0,
        "procurement_title": "Építési beruházás a Szenna Község Önkormányzata Egyedi szennyvíztisztítók kiépítése Szennán",
        "registered_name": "Z. E. H. Energetikai és Építőipari Kft."
    },
    {
        "company_names": "",
        "contract_value": 133784896.0,
        "contracting_authority": "Bőszénfa Községi Önkormányzat",
        "date": "02/03/2018",
        "link_notice": "http://www.kozbeszerzes.hu/ertesito/2018/0/targy/portal_434/megtekint/portal_2793_2018/",
        "main_cpv": "45000000-7",
        "number_companies_win": 0,
        "procurement_title": "Építési beruházás a Bőszénfa Községi Önkormányzat Bőszénfa Község szennyvízkezelési beruházása",
        "registered_name": "Z. E. H. Energetikai és Építőipari Kft."
    },
    {
        "company_names": "",
        "contract_value": 71189242.0,
        "contracting_authority": "Páprád Községi Önkormányzat",
        "date": "17/05/2018",
        "link_notice": "http://www.kozbeszerzes.hu/ertesito/2018/0/targy/portal_434/megtekint/portal_7954_2018/",
        "main_cpv": "45000000-7",
        "number_companies_win": 0,
        "procurement_title": "Páprád szennyvízkezelési beruházása",
        "registered_name": "Z. E. H. Energetikai és Építőipari Kft."
    },
    {
        "company_names": "",
        "contract_value": 71588990.0,
        "contracting_authority": "Kamond Község Önkormányzata",
        "date": "23/07/2019",
        "link_notice": "http://www.kozbeszerzes.hu/ertesito/2019/0/targy/portal_434/megtekint/portal_13765_2019/",
        "main_cpv": "45000000-7",
        "number_companies_win": 0,
        "procurement_title": "Kamond egyedi szennyvízkezelésének megoldása",
        "registered_name": "Z. E. H. Energetikai és Építőipari Kft."
    },
    {
        "company_names": "",
        "contract_value": 109705072.0,
        "contracting_authority": "Egyházasharaszti Önkormányzat",
        "date": "23/01/2020",
        "link_notice": "http://www.kozbeszerzes.hu/ertesito/2020/0/targy/portal_434/megtekint/portal_1218_2020/",
        "main_cpv": "45000000-7",
        "number_companies_win": 0,
        "procurement_title": "Szennyvízkezelési beruházás",
        "registered_name": "Z. E. H. Energetikai és Építőipari Kft."
    },
    {
        "company_names": "",
        "contract_value": 131284012.0,
        "contracting_authority": "Alsószenterzsébet-Felsőszenterzsébet-Kerkafalva-Kerkakutas-Magyarföld Önkormányzati Szennyvízkezelési Társulás",
        "date": "01/04/2020",
        "link_notice": "http://www.kozbeszerzes.hu/ertesito/2020/0/targy/portal_434/megtekint/portal_5729_2020/",
        "main_cpv": "45000000-7",
        "number_companies_win": 0,
        "procurement_title": "Szennyvízkezelési beruházás",
        "registered_name": "Z. E. H. Energetikai és Építőipari Kft."
    },
    {
        "company_names": "",
        "contract_value": 42875394.0,
        "contracting_authority": "Nemesnép Község Önkormányzata",
        "date": "03/06/2020",
        "link_notice": "http://www.kozbeszerzes.hu/ertesito/2020/0/targy/portal_434/megtekint/portal_9634_2020/",
        "main_cpv": "45000000-7",
        "number_companies_win": 0,
        "procurement_title": "Szennyvízkezelési beruházás - Nemesnép",
        "registered_name": "Z. E. H. Energetikai és Építőipari Kft."
    },
    {
        "company_names": "",
        "contract_value": 130672740.0,
        "contracting_authority": "Kémes Községi Önkormányzat",
        "date": "31/07/2020",
        "link_notice": "http://www.kozbeszerzes.hu/ertesito/2020/0/targy/portal_454/megtekint/portal_13964_2020/",
        "main_cpv": "45000000-7",
        "number_companies_win": 0,
        "procurement_title": "Szennyvízkezelési beruházás - Kémes",
        "registered_name": "Z. E. H. Energetikai és Építőipari Kft."
    },
    {
        "company_names": "",
        "contract_value": 103309249.0,
        "contracting_authority": "Úny Község Önkormányzata",
        "date": "17/09/2020",
        "link_notice": "http://www.kozbeszerzes.hu/ertesito/2020/0/targy/portal_434/megtekint/portal_16910_2020/",
        "main_cpv": "45000000-7",
        "number_companies_win": 0,
        "procurement_title": "Szennyvízkezelési beruházás",
        "registered_name": "Z. E. H. Energetikai és Építőipari Kft."
    },
    {
        "company_names": "",
        "contract_value": 40934370.0,
        "contracting_authority": "Orbányosfa Község Önkormányzata",
        "date": "18/09/2020",
        "link_notice": "http://www.kozbeszerzes.hu/ertesito/2020/0/targy/portal_454/megtekint/portal_16850_2020/",
        "main_cpv": "45000000-7",
        "number_companies_win": 0,
        "procurement_title": "Orbányosfa - Szennyvízkezelési beruházás",
        "registered_name": "Z. E. H. Energetikai és Építőipari Kft."
    },
    {
        "company_names": "",
        "contract_value": 122031376.0,
        "contracting_authority": "Tilaj Község Önkormányzata",
        "date": "22/09/2020",
        "link_notice": "http://www.kozbeszerzes.hu/ertesito/2020/0/targy/portal_454/megtekint/portal_17265_2020/",
        "main_cpv": "45000000-7",
        "number_companies_win": 0,
        "procurement_title": "Tilaj - Szennyvízkezelési beruházás",
        "registered_name": "Z. E. H. Energetikai és Építőipari Kft."
    },
    {
        "company_names": "",
        "contract_value": 75953738.0,
        "contracting_authority": "Bezeréd Község Önkormányzata",
        "date": "14/12/2020",
        "link_notice": "http://www.kozbeszerzes.hu/ertesito/2020/0/targy/portal_454/megtekint/portal_23349_2020/",
        "main_cpv": "45000000-7",
        "number_companies_win": 0,
        "procurement_title": "Szennyvízkezelési beruházás Bezeréd",
        "registered_name": "Z. E. H. Energetikai és Építőipari Kft."
    }
]