[
    {
        "company_names": "",
        "contract_value": "31500000",
        "contracting_authority": "Magyar Közút Nonprofit Zártkörűen Működő Részvénytársaság",
        "date": "04/04/2018",
        "link_notice": "http://www.kozbeszerzes.hu/ertesito/2018/0/targy/portal_403/megtekint/portal_5013_2018/",
        "main_cpv": "44113620-7",
        "number_companies_win": 0,
        "procurement_title": "Téli melegaszfalt beszerzés 2017",
        "registered_name": "HARMAT-BAU Építőipari Szolgáltató Korlátolt Felelősségű Társaság"
    },
    {
        "company_names": "",
        "contract_value": "36453846",
        "contracting_authority": "Magyar Közút Nonprofit Zártkörűen Működő Részvénytársaság",
        "date": "27/04/2018",
        "link_notice": "http://www.kozbeszerzes.hu/ertesito/2018/0/targy/portal_403/megtekint/portal_6530_2018/",
        "main_cpv": "44113620-7",
        "number_companies_win": 0,
        "procurement_title": "Melegaszfalt beszerzés-2017.",
        "registered_name": "HARMAT-BAU Építőipari Szolgáltató Korlátolt Felelősségű Társaság"
    },
    {
        "company_names": "",
        "contract_value": "41076923",
        "contracting_authority": "Magyar Közút Nonprofit Zártkörűen Működő Részvénytársaság",
        "date": "27/04/2018",
        "link_notice": "http://www.kozbeszerzes.hu/ertesito/2018/0/targy/portal_403/megtekint/portal_6530_2018/",
        "main_cpv": "44113620-7",
        "number_companies_win": 0,
        "procurement_title": "Melegaszfalt beszerzés-2017.",
        "registered_name": "HARMAT-BAU Építőipari Szolgáltató Korlátolt Felelősségű Társaság"
    },
    {
        "company_names": "",
        "contract_value": "81234059",
        "contracting_authority": "Szeged Megyei Jogú Város Önkormányzata",
        "date": "19/09/2018",
        "link_notice": "http://www.kozbeszerzes.hu/ertesito/2018/0/targy/portal_434/megtekint/portal_16109_2018/",
        "main_cpv": "45233220-7",
        "number_companies_win": 0,
        "procurement_title": "Szeged, Útburkolat rekonstrukciós munkák elvégzése",
        "registered_name": "HARMAT-BAU Építőipari Szolgáltató Korlátolt Felelősségű Társaság"
    },
    {
        "company_names": "",
        "contract_value": "96556055",
        "contracting_authority": "Szeged Megyei Jogú Város Önkormányzata",
        "date": "19/09/2018",
        "link_notice": "http://www.kozbeszerzes.hu/ertesito/2018/0/targy/portal_434/megtekint/portal_16109_2018/",
        "main_cpv": "45233220-7",
        "number_companies_win": 0,
        "procurement_title": "Szeged, Útburkolat rekonstrukciós munkák elvégzése",
        "registered_name": "HARMAT-BAU Építőipari Szolgáltató Korlátolt Felelősségű Társaság"
    },
    {
        "company_names": "",
        "contract_value": "2397000",
        "contracting_authority": "Magyar Közút Nonprofit Zártkörűen Működő Részvénytársaság",
        "date": "03/07/2019",
        "link_notice": "http://www.kozbeszerzes.hu/ertesito/2019/0/targy/portal_403/megtekint/portal_12030_2019/",
        "main_cpv": "44113620-7",
        "number_companies_win": 0,
        "procurement_title": "Melegaszfalt beszerzés 2018 - Dél-Magyarország",
        "registered_name": "HARMAT-BAU Építőipari Szolgáltató Korlátolt Felelősségű Társaság"
    },
    {
        "company_names": "",
        "contract_value": "2399000",
        "contracting_authority": "Magyar Közút Nonprofit Zártkörűen Működő Részvénytársaság",
        "date": "03/07/2019",
        "link_notice": "http://www.kozbeszerzes.hu/ertesito/2019/0/targy/portal_403/megtekint/portal_12030_2019/",
        "main_cpv": "44113620-7",
        "number_companies_win": 0,
        "procurement_title": "Melegaszfalt beszerzés 2018 - Dél-Magyarország",
        "registered_name": "HARMAT-BAU Építőipari Szolgáltató Korlátolt Felelősségű Társaság"
    },
    {
        "company_names": "",
        "contract_value": "115780000",
        "contracting_authority": "Magyar Közút Nonprofit Zártkörűen Működő Részvénytársaság",
        "date": "15/10/2019",
        "link_notice": "http://www.kozbeszerzes.hu/ertesito/2019/0/targy/portal_403/megtekint/portal_19657_2019/",
        "main_cpv": "44113620-7",
        "number_companies_win": 0,
        "procurement_title": "Téli melegaszfalt beszerzés 2019",
        "registered_name": "HARMAT-BAU Építőipari Szolgáltató Korlátolt Felelősségű Társaság"
    },
    {
        "company_names": "",
        "contract_value": "41430475",
        "contracting_authority": "Magyar Közút Nonprofit Zártkörűen Működő Részvénytársaság",
        "date": "08/06/2021",
        "link_notice": "https://www.kozbeszerzes.hu/ertesito/2021/0/targy/portal_403/megtekint/portal_10007_2021/",
        "main_cpv": "44113620-7",
        "number_companies_win": 0,
        "procurement_title": "Melegaszfalt beszerzés 2020 - Dél-Magyarország",
        "registered_name": "HARMAT-BAU Építőipari Szolgáltató Korlátolt Felelősségű Társaság"
    },
    {
        "company_names": "",
        "contract_value": "91987887",
        "contracting_authority": "Magyar Közút Nonprofit Zártkörűen Működő Részvénytársaság",
        "date": "08/06/2021",
        "link_notice": "https://www.kozbeszerzes.hu/ertesito/2021/0/targy/portal_403/megtekint/portal_10007_2021/",
        "main_cpv": "44113620-7",
        "number_companies_win": 0,
        "procurement_title": "Melegaszfalt beszerzés 2020 - Dél-Magyarország",
        "registered_name": "HARMAT-BAU Építőipari Szolgáltató Korlátolt Felelősségű Társaság"
    },
    {
        "company_names": "",
        "contract_value": "99134538",
        "contracting_authority": "Magyar Közút Nonprofit Zártkörűen Működő Részvénytársaság",
        "date": "08/06/2021",
        "link_notice": "https://www.kozbeszerzes.hu/ertesito/2021/0/targy/portal_403/megtekint/portal_10007_2021/",
        "main_cpv": "44113620-7",
        "number_companies_win": 0,
        "procurement_title": "Melegaszfalt beszerzés 2020 - Dél-Magyarország",
        "registered_name": "HARMAT-BAU Építőipari Szolgáltató Korlátolt Felelősségű Társaság"
    },
    {
        "company_names": "",
        "contract_value": "102192772",
        "contracting_authority": "Magyar Közút Nonprofit Zártkörűen Működő Részvénytársaság",
        "date": "08/06/2021",
        "link_notice": "https://www.kozbeszerzes.hu/ertesito/2021/0/targy/portal_403/megtekint/portal_10007_2021/",
        "main_cpv": "44113620-7",
        "number_companies_win": 0,
        "procurement_title": "Melegaszfalt beszerzés 2020 - Dél-Magyarország",
        "registered_name": "HARMAT-BAU Építőipari Szolgáltató Korlátolt Felelősségű Társaság"
    }
]