[
    {
        "company_names": "",
        "contract_value": "135569002",
        "contracting_authority": "Budapesti Módszertani Szociális Központ és Intézményei",
        "date": "28/03/2018",
        "link_notice": "http://www.kozbeszerzes.hu/ertesito/2018/0/targy/portal_403/megtekint/portal_2646_2018/",
        "main_cpv": "90910000-9",
        "number_companies_win": 0,
        "procurement_title": "Budapesti Módszertani Szociális Központ és Intézményei takarítási feladatainak ellátása vállalkozási szerződés keretében",
        "registered_name": "Ferencz-ker Szolgáltató Korlátolt Felelősségű Társaság"
    },
    {
        "company_names": "",
        "contract_value": "166023848",
        "contracting_authority": "Budapesti Módszertani Szociális Központ és Intézményei",
        "date": "28/03/2018",
        "link_notice": "http://www.kozbeszerzes.hu/ertesito/2018/0/targy/portal_403/megtekint/portal_2646_2018/",
        "main_cpv": "90910000-9",
        "number_companies_win": 0,
        "procurement_title": "Budapesti Módszertani Szociális Központ és Intézményei takarítási feladatainak ellátása vállalkozási szerződés keretében",
        "registered_name": "Ferencz-ker Szolgáltató Korlátolt Felelősségű Társaság"
    },
    {
        "company_names": "",
        "contract_value": "13158432",
        "contracting_authority": "Budapesti Gazdasági Egyetem",
        "date": "23/01/2019",
        "link_notice": "http://www.kozbeszerzes.hu/ertesito/2019/0/targy/portal_403/megtekint/portal_0982_2019/",
        "main_cpv": "90910000-9",
        "number_companies_win": 0,
        "procurement_title": "BGE Takarítás 2018.",
        "registered_name": "Ferencz-ker Szolgáltató Korlátolt Felelősségű Társaság"
    },
    {
        "company_names": "",
        "contract_value": "18891044",
        "contracting_authority": "Budapesti Gazdasági Egyetem",
        "date": "23/01/2019",
        "link_notice": "http://www.kozbeszerzes.hu/ertesito/2019/0/targy/portal_403/megtekint/portal_0982_2019/",
        "main_cpv": "90910000-9",
        "number_companies_win": 0,
        "procurement_title": "BGE Takarítás 2018.",
        "registered_name": "Ferencz-ker Szolgáltató Korlátolt Felelősségű Társaság"
    },
    {
        "company_names": "",
        "contract_value": "105937400",
        "contracting_authority": "Budapesti Gazdasági Egyetem",
        "date": "23/01/2019",
        "link_notice": "http://www.kozbeszerzes.hu/ertesito/2019/0/targy/portal_403/megtekint/portal_0982_2019/",
        "main_cpv": "90910000-9",
        "number_companies_win": 0,
        "procurement_title": "BGE Takarítás 2018.",
        "registered_name": "Ferencz-ker Szolgáltató Korlátolt Felelősségű Társaság"
    },
    {
        "company_names": "",
        "contract_value": "269678036",
        "contracting_authority": "Budapesti Módszertani Szociális Központ és Intézményei",
        "date": "12/07/2019",
        "link_notice": "http://www.kozbeszerzes.hu/ertesito/2019/0/targy/portal_403/megtekint/portal_12691_2019/",
        "main_cpv": "90910000-9",
        "number_companies_win": 0,
        "procurement_title": "BMSZKI takarítás 2019",
        "registered_name": "Ferencz-ker Szolgáltató Korlátolt Felelősségű Társaság"
    },
    {
        "company_names": "",
        "contract_value": "330259840",
        "contracting_authority": "Budapesti Módszertani Szociális Központ és Intézményei",
        "date": "12/07/2019",
        "link_notice": "http://www.kozbeszerzes.hu/ertesito/2019/0/targy/portal_403/megtekint/portal_12691_2019/",
        "main_cpv": "90910000-9",
        "number_companies_win": 0,
        "procurement_title": "BMSZKI takarítás 2019",
        "registered_name": "Ferencz-ker Szolgáltató Korlátolt Felelősségű Társaság"
    },
    {
        "company_names": "",
        "contract_value": "80986915",
        "contracting_authority": "Semmelweis Egyetem",
        "date": "19/06/2020",
        "link_notice": "http://www.kozbeszerzes.hu/ertesito/2020/0/targy/portal_403/megtekint/portal_10080_2020/",
        "main_cpv": "90911200-8",
        "number_companies_win": 0,
        "procurement_title": "SE iskoláinak takarítása",
        "registered_name": "Ferencz-ker Szolgáltató Korlátolt Felelősségű Társaság"
    },
    {
        "company_names": "",
        "contract_value": "6090924",
        "contracting_authority": "Eötvös Loránd Tudományegyetem",
        "date": "19/08/2020",
        "link_notice": "http://www.kozbeszerzes.hu/ertesito/2020/0/targy/portal_403/megtekint/portal_14969_2020/",
        "main_cpv": "90910000-9",
        "number_companies_win": 0,
        "procurement_title": "Takarítási feladatok ellátása az ELTE épületeiben",
        "registered_name": "Ferencz-ker Szolgáltató Korlátolt Felelősségű Társaság"
    },
    {
        "company_names": "",
        "contract_value": "11858344",
        "contracting_authority": "Eötvös Loránd Tudományegyetem",
        "date": "19/08/2020",
        "link_notice": "http://www.kozbeszerzes.hu/ertesito/2020/0/targy/portal_403/megtekint/portal_14969_2020/",
        "main_cpv": "90910000-9",
        "number_companies_win": 0,
        "procurement_title": "Takarítási feladatok ellátása az ELTE épületeiben",
        "registered_name": "Ferencz-ker Szolgáltató Korlátolt Felelősségű Társaság"
    },
    {
        "company_names": "",
        "contract_value": "177917072",
        "contracting_authority": "Eötvös Loránd Tudományegyetem",
        "date": "19/08/2020",
        "link_notice": "http://www.kozbeszerzes.hu/ertesito/2020/0/targy/portal_403/megtekint/portal_14969_2020/",
        "main_cpv": "90910000-9",
        "number_companies_win": 0,
        "procurement_title": "Takarítási feladatok ellátása az ELTE épületeiben",
        "registered_name": "Ferencz-ker Szolgáltató Korlátolt Felelősségű Társaság"
    },
    {
        "company_names": "",
        "contract_value": "360000",
        "contracting_authority": "Budapesti Módszertani Szociális Központ és Intézményei",
        "date": "22/12/2020",
        "link_notice": "https://www.kozbeszerzes.hu/ertesito/2020/0/targy/portal_454/megtekint/portal_22617_2020/",
        "main_cpv": "90921000-9",
        "number_companies_win": 0,
        "procurement_title": "Rovar- és rágcsálóirtás a BMSZKI részére 2020/2021",
        "registered_name": "Ferencz-ker Szolgáltató Korlátolt Felelősségű Társaság"
    },
    {
        "company_names": "",
        "contract_value": "8646846",
        "contracting_authority": "Budapesti Módszertani Szociális Központ és Intézményei",
        "date": "22/12/2020",
        "link_notice": "https://www.kozbeszerzes.hu/ertesito/2020/0/targy/portal_454/megtekint/portal_22617_2020/",
        "main_cpv": "90921000-9",
        "number_companies_win": 0,
        "procurement_title": "Rovar- és rágcsálóirtás a BMSZKI részére 2020/2021",
        "registered_name": "Ferencz-ker Szolgáltató Korlátolt Felelősségű Társaság"
    },
    {
        "company_names": "",
        "contract_value": "26113400",
        "contracting_authority": "Országos Atomenergia Hivatal",
        "date": "22/12/2020",
        "link_notice": "https://www.kozbeszerzes.hu/ertesito/2020/0/targy/portal_454/megtekint/portal_23944_2020/",
        "main_cpv": "90919200-4",
        "number_companies_win": 0,
        "procurement_title": "Takarítási szolgáltatás beszerzése",
        "registered_name": "Ferencz-ker Szolgáltató Korlátolt Felelősségű Társaság"
    },
    {
        "company_names": "",
        "contract_value": "132982125",
        "contracting_authority": "Budapesti Gazdasági Egyetem",
        "date": "08/04/2021",
        "link_notice": "https://www.kozbeszerzes.hu/ertesito/2021/0/targy/portal_403/megtekint/portal_5581_2021/",
        "main_cpv": "90910000-9",
        "number_companies_win": 0,
        "procurement_title": "BGE KVIK épületeinek takarítása",
        "registered_name": "Ferencz-ker Szolgáltató Korlátolt Felelősségű Társaság"
    },
    {
        "company_names": "",
        "contract_value": "38695953",
        "contracting_authority": "Budapesti Gazdasági Egyetem",
        "date": "14/05/2021",
        "link_notice": "https://www.kozbeszerzes.hu/ertesito/2021/0/targy/portal_403/megtekint/portal_8539_2021/",
        "main_cpv": "90910000-9",
        "number_companies_win": 0,
        "procurement_title": "PSZK Berzsenyi u. 6. alatti épületének takarítása",
        "registered_name": "Ferencz-ker Szolgáltató Korlátolt Felelősségű Társaság"
    },
    {
        "company_names": "",
        "contract_value": "699984000",
        "contracting_authority": "Budapesti Módszertani Szociális Központ és Intézményei",
        "date": "28/06/2021",
        "link_notice": "https://www.kozbeszerzes.hu/ertesito/2021/0/targy/portal_403/megtekint/portal_11597_2021/",
        "main_cpv": "90910000-9",
        "number_companies_win": 0,
        "procurement_title": "Takarítás a BMSZKI telephelyein 2021-23.",
        "registered_name": "Ferencz-ker Szolgáltató Korlátolt Felelősségű Társaság"
    },
    {
        "company_names": "",
        "contract_value": "52579063",
        "contracting_authority": "XVI. Kerület Kertvárosi Egészségügyi Szolgálata",
        "date": "13/07/2021",
        "link_notice": "https://www.kozbeszerzes.hu/ertesito/2021/0/targy/portal_454/megtekint/portal_13317_2021/",
        "main_cpv": "90900000-6",
        "number_companies_win": 0,
        "procurement_title": "Egészségügyi intézmények takarítása",
        "registered_name": "Ferencz-ker Szolgáltató Korlátolt Felelősségű Társaság"
    },
    {
        "company_names": "",
        "contract_value": "63317385",
        "contracting_authority": "Budapest Főváros XV. Kerületi Önkormányzat Dr. Vass László Egészségügyi Intézmény",
        "date": "07/12/2021",
        "link_notice": "https://www.kozbeszerzes.hu/ertesito/2021/0/targy/portal_454/megtekint/portal_24236_2021/",
        "main_cpv": "90900000-6",
        "number_companies_win": 0,
        "procurement_title": "Takarítási szolgáltatás beszerzése",
        "registered_name": "Ferencz-ker Szolgáltató Korlátolt Felelősségű Társaság"
    },
    {
        "company_names": "",
        "contract_value": "49273895",
        "contracting_authority": "Budapesti Módszertani Szociális Központ és Intézményei",
        "date": "27/12/2021",
        "link_notice": "https://www.kozbeszerzes.hu/ertesito/2021/0/targy/portal_403/megtekint/portal_25490_2021/",
        "main_cpv": "90921000-9",
        "number_companies_win": 0,
        "procurement_title": "Kártevőirtás a BMSZKI telephelyein",
        "registered_name": "Ferencz-ker Szolgáltató Korlátolt Felelősségű Társaság"
    }
]