[
    {
        "company_names": "",
        "contract_value": 21050483.0,
        "contracting_authority": "Sály Község Önkormányzata",
        "date": "22/10/2019",
        "link_notice": "http://www.kozbeszerzes.hu/ertesito/2019/0/targy/portal_434/megtekint/portal_20572_2019/",
        "main_cpv": "45000000-7",
        "number_companies_win": 0,
        "procurement_title": "Önkormányzati épületek korszerűsítése Sályon 2.",
        "registered_name": "Csendlak Kereskedelmi és Szolgáltató Kft."
    },
    {
        "company_names": "",
        "contract_value": 22691205.0,
        "contracting_authority": "Sály Község Önkormányzata",
        "date": "22/10/2019",
        "link_notice": "http://www.kozbeszerzes.hu/ertesito/2019/0/targy/portal_434/megtekint/portal_20572_2019/",
        "main_cpv": "45000000-7",
        "number_companies_win": 0,
        "procurement_title": "Önkormányzati épületek korszerűsítése Sályon 2.",
        "registered_name": "Csendlak Kereskedelmi és Szolgáltató Kft."
    },
    {
        "company_names": "",
        "contract_value": 1009699.0,
        "contracting_authority": "Sály Község Önkormányzata",
        "date": "25/10/2019",
        "link_notice": "http://www.kozbeszerzes.hu/ertesito/2019/0/targy/portal_434/megtekint/portal_20507_2019/",
        "main_cpv": "45000000-7",
        "number_companies_win": 0,
        "procurement_title": "Építési beruházások megvalósítása Sályon",
        "registered_name": "Csendlak Kereskedelmi és Szolgáltató Kft."
    },
    {
        "company_names": "",
        "contract_value": 17367220.0,
        "contracting_authority": "Sály Község Önkormányzata",
        "date": "25/10/2019",
        "link_notice": "http://www.kozbeszerzes.hu/ertesito/2019/0/targy/portal_434/megtekint/portal_20507_2019/",
        "main_cpv": "45000000-7",
        "number_companies_win": 0,
        "procurement_title": "Építési beruházások megvalósítása Sályon",
        "registered_name": "Csendlak Kereskedelmi és Szolgáltató Kft."
    },
    {
        "company_names": "",
        "contract_value": 40212796.0,
        "contracting_authority": "Sály Község Önkormányzata",
        "date": "25/10/2019",
        "link_notice": "http://www.kozbeszerzes.hu/ertesito/2019/0/targy/portal_434/megtekint/portal_20507_2019/",
        "main_cpv": "45000000-7",
        "number_companies_win": 0,
        "procurement_title": "Építési beruházások megvalósítása Sályon",
        "registered_name": "Csendlak Kereskedelmi és Szolgáltató Kft."
    },
    {
        "company_names": "",
        "contract_value": 24413505.0,
        "contracting_authority": "Sály Község Önkormányzata",
        "date": "18/09/2020",
        "link_notice": "http://www.kozbeszerzes.hu/ertesito/2020/0/targy/portal_454/megtekint/portal_17010_2020/",
        "main_cpv": "45000000-7",
        "number_companies_win": 0,
        "procurement_title": "Általános energetikai korszerűsítése",
        "registered_name": "Csendlak Kereskedelmi és Szolgáltató Kft."
    },
    {
        "company_names": "",
        "contract_value": 32270577.0,
        "contracting_authority": "Sály Község Önkormányzata",
        "date": "18/09/2020",
        "link_notice": "http://www.kozbeszerzes.hu/ertesito/2020/0/targy/portal_454/megtekint/portal_17010_2020/",
        "main_cpv": "45000000-7",
        "number_companies_win": 0,
        "procurement_title": "Általános energetikai korszerűsítése",
        "registered_name": "Csendlak Kereskedelmi és Szolgáltató Kft."
    }
]